pi18n/__init__.py
pi18n/translation_service.py
tests/__init__.py
tests/test.py
pi18n-0.1.2.dist-info/METADATA
pi18n-0.1.2.dist-info/WHEEL
pi18n-0.1.2.dist-info/top_level.txt
pi18n-0.1.2.dist-info/RECORD
