Metadata-Version: 2.1
Name: pi18n
Version: 0.1.2
Summary: A Python internationalization (i18n) package
Home-page: UNKNOWN
Author: Alejandro de Felipe
License: MIT
Platform: UNKNOWN
